{
  "id": "vourukashas-glow",
  "type": "artifact",
  "rarity": 5,
  "data": {
    "en": {
      "name": "Vourukasha’s Glow",
      "2p": "HP +20%",
      "4p": "Elemental Skill and Elemental Burst DMG will be increased by 10%. After the equipping character takes DMG, the aforementioned DMG Bonus is increased by 80% for 5s. This effect increase can have 5 stacks. The duration of each stack is counted independently. These effects can be triggered even when the equipping character is not on the field."
    },
    "zh": {
      "name": "花海甘露之光",
      "2p": "生命值提升20%。",
      "4p": "元素战技与元素爆发造成的伤害提升10%；装备者受到伤害后的5秒内，上述伤害提升效果提高80%，该提高效果至多叠加5层，每层持续时间独立计算，处于队伍后台时依然能触发该效果。"
    }
  }
}
